odoo/addons/maintenance_timesheet/README.rst
odoo/addons/maintenance_timesheet/__init__.py
odoo/addons/maintenance_timesheet/__manifest__.py
odoo/addons/maintenance_timesheet/data/demo_maintenance_timesheet.xml
odoo/addons/maintenance_timesheet/i18n/es.po
odoo/addons/maintenance_timesheet/i18n/it.po
odoo/addons/maintenance_timesheet/i18n/maintenance_timesheet.pot
odoo/addons/maintenance_timesheet/migrations/14.0.2.0.0/pre-migration.py
odoo/addons/maintenance_timesheet/models/__init__.py
odoo/addons/maintenance_timesheet/models/hr_timesheet.py
odoo/addons/maintenance_timesheet/models/maintenance_equipment.py
odoo/addons/maintenance_timesheet/models/maintenance_request.py
odoo/addons/maintenance_timesheet/readme/CONTRIBUTORS.rst
odoo/addons/maintenance_timesheet/readme/DESCRIPTION.rst
odoo/addons/maintenance_timesheet/report/maintenance_request_report.xml
odoo/addons/maintenance_timesheet/security/maintenance_timesheet_security.xml
odoo/addons/maintenance_timesheet/static/description/icon.png
odoo/addons/maintenance_timesheet/static/description/index.html
odoo/addons/maintenance_timesheet/tests/__init__.py
odoo/addons/maintenance_timesheet/tests/test_maintenance_timesheet.py
odoo/addons/maintenance_timesheet/views/hr_timesheet_views.xml
odoo/addons/maintenance_timesheet/views/maintenance_request_views.xml
odoo14_addon_maintenance_timesheet-14.0.2.1.1.dist-info/METADATA
odoo14_addon_maintenance_timesheet-14.0.2.1.1.dist-info/WHEEL
odoo14_addon_maintenance_timesheet-14.0.2.1.1.dist-info/top_level.txt
odoo14_addon_maintenance_timesheet-14.0.2.1.1.dist-info/RECORD
